mapstore2_adapter/__init__.py
mapstore2_adapter/apps.py
mapstore2_adapter/conf.py
mapstore2_adapter/context_processors.py
mapstore2_adapter/converters.py
mapstore2_adapter/hooks.py
mapstore2_adapter/settings.py
mapstore2_adapter/urls.py
mapstore2_adapter/utils.py
mapstore2_adapter/api/__init__.py
mapstore2_adapter/api/models.py
mapstore2_adapter/api/serializers.py
mapstore2_adapter/api/urls.py
mapstore2_adapter/api/views.py
mapstore2_adapter/migrations/0001_initial.py
mapstore2_adapter/migrations/0002_auto_20190618_1236.py
mapstore2_adapter/migrations/0003_auto_20200310_0848.py
mapstore2_adapter/migrations/__init__.py
mapstore2_adapter/plugins/__init__.py
mapstore2_adapter/plugins/geonode.py
mapstore2_adapter/plugins/serializers.py
django_mapstore_adapter-2.0.6.dist-info/AUTHORS
django_mapstore_adapter-2.0.6.dist-info/LICENSE
django_mapstore_adapter-2.0.6.dist-info/METADATA
django_mapstore_adapter-2.0.6.dist-info/WHEEL
django_mapstore_adapter-2.0.6.dist-info/top_level.txt
django_mapstore_adapter-2.0.6.dist-info/RECORD
