Metadata-Version: 2.1
Name: django-mapstore-adapter
Version: 2.0.6
Summary: Django MapStore2 Adapter
Home-page: https://github.com/GeoNode/django-mapstore-adapter
Author: Alessio Fabiani
Author-email: alessio.fabiani@geo-solutions.it
License: UNKNOWN
Download-URL: https://github.com/GeoNode/django-mapstore-adapter/tarball/master
Keywords: django,mapstore,mapstore2
Platform: UNKNOWN
Classifier: Development Status :: 5 - Production/Stable
Classifier: Environment :: Web Environment
Classifier: Framework :: Django
Classifier: Intended Audience :: Developers
Classifier: License :: OSI Approved :: BSD License
Classifier: Operating System :: OS Independent
Classifier: Topic :: Internet :: WWW/HTTP
Classifier: Programming Language :: Python :: 3
Classifier: Programming Language :: Python :: 3.6
Classifier: Programming Language :: Python :: 3.7
Requires-Dist: django (<3.0,>=2.2.0)
Requires-Dist: idna (<2.11,>=2.5)
Requires-Dist: requests (>=2.13.0)
Requires-Dist: Markdown (>=2.6.11)
Requires-Dist: MarkupSafe (>=1.1.1)
Requires-Dist: djangorestframework (<=3.12.1,>=3.8.2)
Requires-Dist: jsonfield (>=2.0.2)
Requires-Dist: urllib3 (>=1.25)
